monsterapi/InputDataModels.py
monsterapi/__init__.py
monsterapi/client.py
monsterapi_v2-0.1.0.dist-info/LICENSE
monsterapi_v2-0.1.0.dist-info/METADATA
monsterapi_v2-0.1.0.dist-info/WHEEL
monsterapi_v2-0.1.0.dist-info/top_level.txt
monsterapi_v2-0.1.0.dist-info/RECORD
